BoxUtils/__init__.py
BoxUtils/box_utils.py
BoxUtils/sample_usage.py
boxutils-0.1.10.dist-info/licenses/LICENSE
tests/__init__.py
boxutils-0.1.10.dist-info/METADATA
boxutils-0.1.10.dist-info/WHEEL
boxutils-0.1.10.dist-info/top_level.txt
boxutils-0.1.10.dist-info/RECORD
