Metadata-Version: 2.4
Name: BoxUtils
Version: 0.1.10
Summary: A utility package for performing Box file and folder operations with a service account
Home-page: https://github.com/kelvinlim/BoxUtils
Author: Kelvin O. Lim
Author-email: lim.kelvino@gmail.com
Classifier: Development Status :: 3 - Alpha
Classifier: Intended Audience :: Developers
Classifier: License :: OSI Approved :: MIT License
Classifier: Programming Language :: Python :: 3.8
Classifier: Programming Language :: Python :: 3.9
Classifier: Programming Language :: Python :: 3.10
License-File: LICENSE
Requires-Dist: python-dotenv
Requires-Dist: box_sdk_gen[jwt]
Dynamic: author
Dynamic: author-email
Dynamic: classifier
Dynamic: description
Dynamic: description-content-type
Dynamic: home-page
Dynamic: license-file
Dynamic: requires-dist
Dynamic: summary
